gbt/__init__.py
gbt/api.py
gbt/dataset.py
gbt/dataset_preprocessor.py
gbt/feature_transformer.py
gbt/lightgbm_model.py
gbt/metrics.py
gbt/params_preset.py
gbt/training_pipeline.py
gbt/version.py
gbt-0.2.dist-info/LICENSE
gbt-0.2.dist-info/METADATA
gbt-0.2.dist-info/WHEEL
gbt-0.2.dist-info/top_level.txt
gbt-0.2.dist-info/RECORD
