Metadata-Version: 2.1
Name: gbt
Version: 0.2
Summary: A gradient boosted tree library with automatic feature engineering.
Home-page: https://github.com/zzsi/gbt
Author: Zhangzhang Si
Author-email: zhangzhang.si@gmail.com
License: MIT
Requires-Python: >=3.6
License-File: LICENSE
Requires-Dist: pandas
Requires-Dist: lightgbm >=2
Requires-Dist: scikit-learn
